dbms/__init__.py
dbms/dbms_abs.py
dbms/mssql_con.py
dbms/mysql_con.py
dbms/postgres_con.py
dbms/sf_con.py
dbms/test_main.py
dbmsValCheck-0.0.3.dist-info/LICENSE
dbmsValCheck-0.0.3.dist-info/METADATA
dbmsValCheck-0.0.3.dist-info/WHEEL
dbmsValCheck-0.0.3.dist-info/top_level.txt
dbmsValCheck-0.0.3.dist-info/RECORD
