Metadata-Version: 2.1
Name: dbmsValCheck
Version: 0.0.3
Summary: The tool for checking validation of a variety of DBMS
Home-page: https://github.com/ojjy/dbmsValCheck
Author: Able Analytics LLC
Author-email: yjjo@able-analytics.com
License: UNKNOWN
Project-URL: Bug Tracker, https://github.com/ojjy/dbmsValCheck/issues
Platform: UNKNOWN
Classifier: Programming Language :: Python :: 3
Classifier: License :: OSI Approved :: MIT License
Classifier: Operating System :: OS Independent
Requires-Python: >=3.6
License-File: LICENSE
